datapizza/embedders/google/__init__.py
datapizza/embedders/google/google.py
datapizza_ai_embedders_google-0.0.5.dist-info/METADATA
datapizza_ai_embedders_google-0.0.5.dist-info/WHEEL
datapizza_ai_embedders_google-0.0.5.dist-info/RECORD
